project05/pld2/pldrom_test2.vhd
library ieee;
use ieee.std_logic_1164.all;

entity pldrom is
    port(
        addr: in std_logic_vector(3 downto 0);
        data: out std_logic_vector(9 downto 0)
    );
end entity;

architecture ROM_arch of pldrom is
begin
    data <= 
    "0001110000" when addr = "0000" else -- move 11111111 to the LR    
    "0011100000" when addr = "0001" else -- move 0000 from the IR to the high 4 bits of the ACC
    "0010100010" when addr = "0010" else -- move 0010 from the IR to the low 4 bits of the ACC
    "0100000100" when addr = "0011" else -- Add ACC to LR and put it back into the LR
    "0100000100" when addr = "0100" else -- Add ACC to LR and put it back into the LR
    "0100100100" when addr = "0101" else -- Subtract ACC from LR and put it back into the LR
    "0101001100" when addr = "0110" else -- Shift the LR left and write it back to the LR
    "0101101100" when addr = "0111" else -- Shift the LR right and write it back to the LR
    "0111101100" when addr = "1000" else -- Rotate the LR right and write it back to the LR
    "0101101100" when addr = "1001" else -- Shift the LR right and write it back to the LR
    "0110011100" when addr = "1010" else -- XOR the LR with all 1s and write it back to the LR (bit inversion)
    "0110110101" when addr = "1011" else -- AND the LR with 01 (sign-extended)
    "0100010110" when addr = "1100" else -- ADD the LR with 10 (sign-extended)
    "1111111111";                        -- garbage	
end ROM_arch;

project05/pld2/pld2.vhd
library ieee;
use ieee.std_logic_1164.all;
use ieee.numeric_std.all;

entity pld2 is
  port(
    clk, reset : in std_logic;
    lights : out std_logic_vector(7 downto 0)
  );
end entity;

architecture FSM_arch of pld2 is
  -- Define states
  type state_type is (sFetch, sExecute1, sExecute2);
  signal state: state_type;

  signal IR: std_logic_vector(9 downto 0);
  signal ROMvalue: std_logic_vector(9 downto 0);
  signal PC: unsigned(3 downto 0);
  signal ACC, SRC: unsigned(7 downto 0);
  signal LR: unsigned(7 downto 0);

  -- Component declaration for ROM
  component pldrom is
    port(
      addr: in std_logic_vector(3 downto 0);
      data: out std_logic_vector(9 downto 0)
    );
  end component;

begin
  process(clk, reset)
  begin
    if reset = '0' then
      IR <= "0000000000";
      PC <= "0000";
      LR <= "00000000";
      state <= sFetch;
    elsif rising_edge(clk) then
      case state is
        when sFetch =>
          IR <= ROMvalue;
          PC <= PC + 1;
          state <= sExecute1;

        when sExecute1 =>
          case IR(9 downto 8) is
            when "00" => -- move 
              case IR(5 downto 4) is
                when "00" => SRC <= ACC;
                when "01" => SRC <= LR;
                when "10" =>
                  SRC <= (others => IR(3)); -- sign extend
                  SRC(2 downto 0) <= unsigned(IR(2 downto 0));
                when others => SRC <= "11111111";
              end case;

            when "01" => -- binary operation
              case IR(4 downto 3) is
                when "00" => SRC <= ACC;
                when "01" => SRC <= LR;
                when "10" =>
                  SRC <= (others => IR(1)); -- sign extend
                  SRC(0) <= IR(0); 
                when others => SRC <= "11111111";
              end case;

            when "10" => -- unconditional branch
              PC <= unsigned(IR(3 downto 0));

            when others => -- conditional branch
              if IR(7) = '0' then
                if ACC = "00000000" then
                  PC <= unsigned(IR(3 downto 0));
                end if;
              else
                if LR = "00000000" then
                  PC <= unsigned(IR(3 downto 0));
                end if;
              end if;
          end case;
          state <= sExecute2;

        when sExecute2 =>
          if IR(9 downto 8) = "00" then -- move
            case IR(7 downto 6) is
              when "00" => ACC <= SRC;
              when "01" => LR <= SRC;
              when "10" => ACC(3 downto 0) <= SRC(3 downto 0);
              when others => ACC(7 downto 4) <= SRC(3 downto 0);
            end case;
          elsif IR(9 downto 8) = "01" then -- binary operation
						case IR(7 downto 5) is
              when "000" => -- add
                if IR(2) = '1' then
                  LR <= LR + SRC;
                else
                  ACC <= ACC + SRC;
                end if;
              when "001" => -- sub 
                if IR(2) = '1' then
                  LR <= LR - SRC;
                else
                  ACC <= ACC - SRC;
                end if;
              when "010" => -- shift left
                if IR(2) = '1' then
                  LR <= LR(6 downto 0) & '0';
                else
                  ACC <= ACC(6 downto 0) & '0';
                end if;
              when "011" => -- shift right maintain sign
                if IR(2) = '1' then
                  LR <= LR(7) & LR(7 downto 1);
                else
                  ACC <= ACC(7)& ACC(7 downto 1);
                end if;
              when "100" => -- xor
                if IR(2) = '1' then
                  LR <= LR xor SRC;
                else
                  ACC <= ACC xor SRC;
                end if;
              when "101" => -- and
                if IR(2) = '1' then
                  LR <= LR and SRC;
                else
                  ACC <= ACC and SRC;
                end if;
              when "110" => -- rotate left
                if IR(2) = '1' then
                  LR <= LR(6 downto 0) & LR(7);
                else
                  ACC <= ACC(6 downto 0) & ACC(7);
                end if;
              when others => -- rotate right
                if IR(2) = '1' then
                  LR <= LR(0) & LR(7 downto 1);
                else
                  ACC <= ACC(0) & ACC(7 downto 1);
                end if;
                --end case;
            end case;
          end if;
          state <= sFetch;
      end case;
    end if;
  end process;

  -- Output Lights Handling
  lights <= std_logic_vector(LR);
  
  ROM_Instance: pldrom port map(
    addr => std_logic_vector(PC),
    data => ROMvalue
  );

end FSM_arch;

project05/pld2/pldbench.vhd
-- Bruce A. Maxwell
-- Spring 2013
-- CS 232
--
-- test program for the lights circuit
--

library ieee;
use ieee.std_logic_1164.all;
use ieee.numeric_std.all;

entity pldbench is
end entity;

architecture test of pldbench is
  -- Adjusted clock cycles in next line to give as many as needed
  constant num_cycles : integer := 400;

  -- this circuit just needs a clock and a reset
  signal clk : std_logic := '1';
  signal reset : std_logic;

  -- lights component
  component pld2
    port( clk, reset : in std_logic;
          lights     : out std_logic_vector(7 downto 0) );
  end component;

  -- output signal
  signal lightsig : std_logic_vector(7 downto 0);

begin

  -- start off with a short reset
  reset <= '0', '1' after 5 ns;

  -- create a clock
  process begin
    for i in 1 to num_cycles loop
      clk <= not clk;
      wait for 5 ns;
      clk <= not clk;
      wait for 5 ns;
    end loop;
    wait;
  end process;

  -- port map the circuit
  L0: pld2 port map( clk, reset, lightsig );

end test;

project05/pld2/pldbench.vcd
$date
  Mon Oct 30 20:36:05 2023
$end
$version
  GHDL v0
$end
$timescale
  1 fs
$end
$scope module standard $end
$upscope $end
$scope module std_logic_1164 $end
$upscope $end
$scope module numeric_std $end
$upscope $end
$scope module pldbench $end
$var reg 1 ! clk $end
$var reg 1 " reset $end
$var reg 8 # lightsig[7:0] $end
$scope module l0 $end
$var reg 1 $ clk $end
$var reg 1 % reset $end
$var reg 8 & lights[7:0] $end
$comment state is not handled $end
$var reg 10 ' ir[9:0] $end
$var reg 10 ( romvalue[9:0] $end
$var reg 4 ) pc[3:0] $end
$var reg 8 * acc[7:0] $end
$var reg 8 + src[7:0] $end
$var reg 8 , lr[7:0] $end
$scope module rom_instance $end
$var reg 4 - addr[3:0] $end
$var reg 10 . data[9:0] $end
$upscope $end
$upscope $end
$upscope $end
$enddefinitions $end
#0
0!
0"
b00000000 #
0$
0%
b00000000 &
b0000000000 '
b0010100000 (
b0000 )
bUUUUUUUU *
bUUUUUUUU +
b00000000 ,
b0000 -
b0010100000 .
#5000000
1!
1"
1$
1%
b0010100000 '
b0011100001 (
b0001 )
b0001 -
b0011100001 .
#10000000
0!
0$
#15000000
1!
1$
b00000000 +
#20000000
0!
0$
#25000000
1!
1$
bUUUU0000 *
#30000000
0!
0$
#35000000
1!
1$
b0011100001 '
b0001000000 (
b0010 )
b0010 -
b0001000000 .
#40000000
0!
0$
#45000000
1!
1$
b00000001 +
#50000000
0!
0$
#55000000
1!
1$
b00010000 *
#60000000
0!
0$
#65000000
1!
1$
b0001000000 '
b0100110101 (
b0011 )
b0011 -
b0100110101 .
#70000000
0!
0$
#75000000
1!
1$
b00010000 +
#80000000
0!
0$
#85000000
1!
b00010000 #
1$
b00010000 &
b00010000 ,
#90000000
0!
0$
#95000000
1!
1$
b0100110101 '
b1110000110 (
b0100 )
b0100 -
b1110000110 .
#100000000
0!
0$
#105000000
1!
1$
b00000001 +
#110000000
0!
0$
#115000000
1!
b00001111 #
1$
b00001111 &
b00001111 ,
#120000000
0!
0$
#125000000
1!
1$
b1110000110 '
b1000000011 (
b0101 )
b0101 -
b1000000011 .
#130000000
0!
0$
#135000000
1!
1$
#140000000
0!
0$
#145000000
1!
1$
#150000000
0!
0$
#155000000
1!
1$
b1000000011 '
b0010101000 (
b0110 )
b0110 -
b0010101000 .
#160000000
0!
0$
#165000000
1!
1$
b0100110101 (
b0011 )
b0011 -
b0100110101 .
#170000000
0!
0$
#175000000
1!
1$
#180000000
0!
0$
#185000000
1!
1$
b0100110101 '
b1110000110 (
b0100 )
b0100 -
b1110000110 .
#190000000
0!
0$
#195000000
1!
1$
#200000000
0!
0$
#205000000
1!
b00001110 #
1$
b00001110 &
b00001110 ,
#210000000
0!
0$
#215000000
1!
1$
b1110000110 '
b1000000011 (
b0101 )
b0101 -
b1000000011 .
#220000000
0!
0$
#225000000
1!
1$
#230000000
0!
0$
#235000000
1!
1$
#240000000
0!
0$
#245000000
1!
1$
b1000000011 '
b0010101000 (
b0110 )
b0110 -
b0010101000 .
#250000000
0!
0$
#255000000
1!
1$
b0100110101 (
b0011 )
b0011 -
b0100110101 .
#260000000
0!
0$
#265000000
1!
1$
#270000000
0!
0$
#275000000
1!
1$
b0100110101 '
b1110000110 (
b0100 )
b0100 -
b1110000110 .
#280000000
0!
0$
#285000000
1!
1$
#290000000
0!
0$
#295000000
1!
b00001101 #
1$
b00001101 &
b00001101 ,
#300000000
0!
0$
#305000000
1!
1$
b1110000110 '
b1000000011 (
b0101 )
b0101 -
b1000000011 .
#310000000
0!
0$
#315000000
1!
1$
#320000000
0!
0$
#325000000
1!
1$
#330000000
0!
0$
#335000000
1!
1$
b1000000011 '
b0010101000 (
b0110 )
b0110 -
b0010101000 .
#340000000
0!
0$
#345000000
1!
1$
b0100110101 (
b0011 )
b0011 -
b0100110101 .
#350000000
0!
0$
#355000000
1!
1$
#360000000
0!
0$
#365000000
1!
1$
b0100110101 '
b1110000110 (
b0100 )
b0100 -
b1110000110 .
#370000000
0!
0$
#375000000
1!
1$
#380000000
0!
0$
#385000000
1!
b00001100 #
1$
b00001100 &
b00001100 ,
#390000000
0!
0$
#395000000
1!
1$
b1110000110 '
b1000000011 (
b0101 )
b0101 -
b1000000011 .
#400000000
0!
0$
#405000000
1!
1$
#410000000
0!
0$
#415000000
1!
1$
#420000000
0!
0$
#425000000
1!
1$
b1000000011 '
b0010101000 (
b0110 )
b0110 -
b0010101000 .
#430000000
0!
0$
#435000000
1!
1$
b0100110101 (
b0011 )
b0011 -
b0100110101 .
#440000000
0!
0$
#445000000
1!
1$
#450000000
0!
0$
#455000000
1!
1$
b0100110101 '
b1110000110 (
b0100 )
b0100 -
b1110000110 .
#460000000
0!
0$
#465000000
1!
1$
#470000000
0!
0$
#475000000
1!
b00001011 #
1$
b00001011 &
b00001011 ,
#480000000
0!
0$
#485000000
1!
1$
b1110000110 '
b1000000011 (
b0101 )
b0101 -
b1000000011 .
#490000000
0!
0$
#495000000
1!
1$
#500000000
0!
0$
#505000000
1!
1$
#510000000
0!
0$
#515000000
1!
1$
b1000000011 '
b0010101000 (
b0110 )
b0110 -
b0010101000 .
#520000000
0!
0$
#525000000
1!
1$
b0100110101 (
b0011 )
b0011 -
b0100110101 .
#530000000
0!
0$
#535000000
1!
1$
#540000000
0!
0$
#545000000
1!
1$
b0100110101 '
b1110000110 (
b0100 )
b0100 -
b1110000110 .
#550000000
0!
0$
#555000000
1!
1$
#560000000
0!
0$
#565000000
1!
b00001010 #
1$
b00001010 &
b00001010 ,
#570000000
0!
0$
#575000000
1!
1$
b1110000110 '
b1000000011 (
b0101 )
b0101 -
b1000000011 .
#580000000
0!
0$
#585000000
1!
1$
#590000000
0!
0$
#595000000
1!
1$
#600000000
0!
0$
#605000000
1!
1$
b1000000011 '
b0010101000 (
b0110 )
b0110 -
b0010101000 .
#610000000
0!
0$
#615000000
1!
1$
b0100110101 (
b0011 )
b0011 -
b0100110101 .
#620000000
0!
0$
#625000000
1!
1$
#630000000
0!
0$
#635000000
1!
1$
b0100110101 '
b1110000110 (
b0100 )
b0100 -
b1110000110 .
#640000000
0!
0$
#645000000
1!
1$
#650000000
0!
0$
#655000000
1!
b00001001 #
1$
b00001001 &
b00001001 ,
#660000000
0!
0$
#665000000
1!
1$
b1110000110 '
b1000000011 (
b0101 )
b0101 -
b1000000011 .
#670000000
0!
0$
#675000000
1!
1$
#680000000
0!
0$
#685000000
1!
1$
#690000000
0!
0$
#695000000
1!
1$
b1000000011 '
b0010101000 (
b0110 )
b0110 -
b0010101000 .
#700000000
0!
0$
#705000000
1!
1$
b0100110101 (
b0011 )
b0011 -
b0100110101 .
#710000000
0!
0$
#715000000
1!
1$
#720000000
0!
0$
#725000000
1!
1$
b0100110101 '
b1110000110 (
b0100 )
b0100 -
b1110000110 .
#730000000
0!
0$
#735000000
1!
1$
#740000000
0!
0$
#745000000
1!
b00001000 #
1$
b00001000 &
b00001000 ,
#750000000
0!
0$
#755000000
1!
1$
b1110000110 '
b1000000011 (
b0101 )
b0101 -
b1000000011 .
#760000000
0!
0$
#765000000
1!
1$
#770000000
0!
0$
#775000000
1!
1$
#780000000
0!
0$
#785000000
1!
1$
b1000000011 '
b0010101000 (
b0110 )
b0110 -
b0010101000 .
#790000000
0!
0$
#795000000
1!
1$
b0100110101 (
b0011 )
b0011 -
b0100110101 .
#800000000
0!
0$
#805000000
1!
1$
#810000000
0!
0$
#815000000
1!
1$
b0100110101 '
b1110000110 (
b0100 )
b0100 -
b1110000110 .
#820000000
0!
0$
#825000000
1!
1$
#830000000
0!
0$
#835000000
1!
b00000111 #
1$
b00000111 &
b00000111 ,
#840000000
0!
0$
#845000000
1!
1$
b1110000110 '
b1000000011 (
b0101 )
b0101 -
b1000000011 .
#850000000
0!
0$
#855000000
1!
1$
#860000000
0!
0$
#865000000
1!
1$
#870000000
0!
0$
#875000000
1!
1$
b1000000011 '
b0010101000 (
b0110 )
b0110 -
b0010101000 .
#880000000
0!
0$
#885000000
1!
1$
b0100110101 (
b0011 )
b0011 -
b0100110101 .
#890000000
0!
0$
#895000000
1!
1$
#900000000
0!
0$
#905000000
1!
1$
b0100110101 '
b1110000110 (
b0100 )
b0100 -
b1110000110 .
#910000000
0!
0$
#915000000
1!
1$
#920000000
0!
0$
#925000000
1!
b00000110 #
1$
b00000110 &
b00000110 ,
#930000000
0!
0$
#935000000
1!
1$
b1110000110 '
b1000000011 (
b0101 )
b0101 -
b1000000011 .
#940000000
0!
0$
#945000000
1!
1$
#950000000
0!
0$
#955000000
1!
1$
#960000000
0!
0$
#965000000
1!
1$
b1000000011 '
b0010101000 (
b0110 )
b0110 -
b0010101000 .
#970000000
0!
0$
#975000000
1!
1$
b0100110101 (
b0011 )
b0011 -
b0100110101 .
#980000000
0!
0$
#985000000
1!
1$
#990000000
0!
0$
#995000000
1!
1$
b0100110101 '
b1110000110 (
b0100 )
b0100 -
b1110000110 .
#1000000000
0!
0$
#1005000000
1!
1$
#1010000000
0!
0$
#1015000000
1!
b00000101 #
1$
b00000101 &
b00000101 ,
#1020000000
0!
0$
#1025000000
1!
1$
b1110000110 '
b1000000011 (
b0101 )
b0101 -
b1000000011 .
#1030000000
0!
0$
#1035000000
1!
1$
#1040000000
0!
0$
#1045000000
1!
1$
#1050000000
0!
0$
#1055000000
1!
1$
b1000000011 '
b0010101000 (
b0110 )
b0110 -
b0010101000 .
#1060000000
0!
0$
#1065000000
1!
1$
b0100110101 (
b0011 )
b0011 -
b0100110101 .
#1070000000
0!
0$
#1075000000
1!
1$
#1080000000
0!
0$
#1085000000
1!
1$
b0100110101 '
b1110000110 (
b0100 )
b0100 -
b1110000110 .
#1090000000
0!
0$
#1095000000
1!
1$
#1100000000
0!
0$
#1105000000
1!
b00000100 #
1$
b00000100 &
b00000100 ,
#1110000000
0!
0$
#1115000000
1!
1$
b1110000110 '
b1000000011 (
b0101 )
b0101 -
b1000000011 .
#1120000000
0!
0$
#1125000000
1!
1$
#1130000000
0!
0$
#1135000000
1!
1$
#1140000000
0!
0$
#1145000000
1!
1$
b1000000011 '
b0010101000 (
b0110 )
b0110 -
b0010101000 .
#1150000000
0!
0$
#1155000000
1!
1$
b0100110101 (
b0011 )
b0011 -
b0100110101 .
#1160000000
0!
0$
#1165000000
1!
1$
#1170000000
0!
0$
#1175000000
1!
1$
b0100110101 '
b1110000110 (
b0100 )
b0100 -
b1110000110 .
#1180000000
0!
0$
#1185000000
1!
1$
#1190000000
0!
0$
#1195000000
1!
b00000011 #
1$
b00000011 &
b00000011 ,
#1200000000
0!
0$
#1205000000
1!
1$
b1110000110 '
b1000000011 (
b0101 )
b0101 -
b1000000011 .
#1210000000
0!
0$
#1215000000
1!
1$
#1220000000
0!
0$
#1225000000
1!
1$
#1230000000
0!
0$
#1235000000
1!
1$
b1000000011 '
b0010101000 (
b0110 )
b0110 -
b0010101000 .
#1240000000
0!
0$
#1245000000
1!
1$
b0100110101 (
b0011 )
b0011 -
b0100110101 .
#1250000000
0!
0$
#1255000000
1!
1$
#1260000000
0!
0$
#1265000000
1!
1$
b0100110101 '
b1110000110 (
b0100 )
b0100 -
b1110000110 .
#1270000000
0!
0$
#1275000000
1!
1$
#1280000000
0!
0$
#1285000000
1!
b00000010 #
1$
b00000010 &
b00000010 ,
#1290000000
0!
0$
#1295000000
1!
1$
b1110000110 '
b1000000011 (
b0101 )
b0101 -
b1000000011 .
#1300000000
0!
0$
#1305000000
1!
1$
#1310000000
0!
0$
#1315000000
1!
1$
#1320000000
0!
0$
#1325000000
1!
1$
b1000000011 '
b0010101000 (
b0110 )
b0110 -
b0010101000 .
#1330000000
0!
0$
#1335000000
1!
1$
b0100110101 (
b0011 )
b0011 -
b0100110101 .
#1340000000
0!
0$
#1345000000
1!
1$
#1350000000
0!
0$
#1355000000
1!
1$
b0100110101 '
b1110000110 (
b0100 )
b0100 -
b1110000110 .
#1360000000
0!
0$
#1365000000
1!
1$
#1370000000
0!
0$
#1375000000
1!
b00000001 #
1$
b00000001 &
b00000001 ,
#1380000000
0!
0$
#1385000000
1!
1$
b1110000110 '
b1000000011 (
b0101 )
b0101 -
b1000000011 .
#1390000000
0!
0$
#1395000000
1!
1$
#1400000000
0!
0$
#1405000000
1!
1$
#1410000000
0!
0$
#1415000000
1!
1$
b1000000011 '
b0010101000 (
b0110 )
b0110 -
b0010101000 .
#1420000000
0!
0$
#1425000000
1!
1$
b0100110101 (
b0011 )
b0011 -
b0100110101 .
#1430000000
0!
0$
#1435000000
1!
1$
#1440000000
0!
0$
#1445000000
1!
1$
b0100110101 '
b1110000110 (
b0100 )
b0100 -
b1110000110 .
#1450000000
0!
0$
#1455000000
1!
1$
#1460000000
0!
0$
#1465000000
1!
b00000000 #
1$
b00000000 &
b00000000 ,
#1470000000
0!
0$
#1475000000
1!
1$
b1110000110 '
b1000000011 (
b0101 )
b0101 -
b1000000011 .
#1480000000
0!
0$
#1485000000
1!
1$
b0010101000 (
b0110 )
b0110 -
b0010101000 .
#1490000000
0!
0$
#1495000000
1!
1$
#1500000000
0!
0$
#1505000000
1!
1$
b0010101000 '
b0011100000 (
b0111 )
b0111 -
b0011100000 .
#1510000000
0!
0$
#1515000000
1!
1$
b11111000 +
#1520000000
0!
0$
#1525000000
1!
1$
b00011000 *
#1530000000
0!
0$
#1535000000
1!
1$
b0011100000 '
b0001110000 (
b1000 )
b1000 -
b0001110000 .
#1540000000
0!
0$
#1545000000
1!
1$
b00000000 +
#1550000000
0!
0$
#1555000000
1!
1$
b00001000 *
#1560000000
0!
0$
#1565000000
1!
1$
b0001110000 '
b0001100000 (
b1001 )
b1001 -
b0001100000 .
#1570000000
0!
0$
#1575000000
1!
1$
b11111111 +
#1580000000
0!
0$
#1585000000
1!
b11111111 #
1$
b11111111 &
b11111111 ,
#1590000000
0!
0$
#1595000000
1!
1$
b0001100000 '
b0100110001 (
b1010 )
b1010 -
b0100110001 .
#1600000000
0!
0$
#1605000000
1!
1$
b00000000 +
#1610000000
0!
0$
#1615000000
1!
b00000000 #
1$
b00000000 &
b00000000 ,
#1620000000
0!
0$
#1625000000
1!
1$
b0100110001 '
b1100000000 (
b1011 )
b1011 -
b1100000000 .
#1630000000
0!
0$
#1635000000
1!
1$
b00000001 +
#1640000000
0!
0$
#1645000000
1!
1$
b00000111 *
#1650000000
0!
0$
#1655000000
1!
1$
b1100000000 '
b1000001000 (
b1100 )
b1100 -
b1000001000 .
#1660000000
0!
0$
#1665000000
1!
1$
#1670000000
0!
0$
#1675000000
1!
1$
#1680000000
0!
0$
#1685000000
1!
1$
b1000001000 '
b0000000000 (
b1101 )
b1101 -
b0000000000 .
#1690000000
0!
0$
#1695000000
1!
1$
b0001110000 (
b1000 )
b1000 -
b0001110000 .
#1700000000
0!
0$
#1705000000
1!
1$
#1710000000
0!
0$
#1715000000
1!
1$
b0001110000 '
b0001100000 (
b1001 )
b1001 -
b0001100000 .
#1720000000
0!
0$
#1725000000
1!
1$
b11111111 +
#1730000000
0!
0$
#1735000000
1!
b11111111 #
1$
b11111111 &
b11111111 ,
#1740000000
0!
0$
#1745000000
1!
1$
b0001100000 '
b0100110001 (
b1010 )
b1010 -
b0100110001 .
#1750000000
0!
0$
#1755000000
1!
1$
b00000000 +
#1760000000
0!
0$
#1765000000
1!
b00000000 #
1$
b00000000 &
b00000000 ,
#1770000000
0!
0$
#1775000000
1!
1$
b0100110001 '
b1100000000 (
b1011 )
b1011 -
b1100000000 .
#1780000000
0!
0$
#1785000000
1!
1$
b00000001 +
#1790000000
0!
0$
#1795000000
1!
1$
b00000110 *
#1800000000
0!
0$
#1805000000
1!
1$
b1100000000 '
b1000001000 (
b1100 )
b1100 -
b1000001000 .
#1810000000
0!
0$
#1815000000
1!
1$
#1820000000
0!
0$
#1825000000
1!
1$
#1830000000
0!
0$
#1835000000
1!
1$
b1000001000 '
b0000000000 (
b1101 )
b1101 -
b0000000000 .
#1840000000
0!
0$
#1845000000
1!
1$
b0001110000 (
b1000 )
b1000 -
b0001110000 .
#1850000000
0!
0$
#1855000000
1!
1$
#1860000000
0!
0$
#1865000000
1!
1$
b0001110000 '
b0001100000 (
b1001 )
b1001 -
b0001100000 .
#1870000000
0!
0$
#1875000000
1!
1$
b11111111 +
#1880000000
0!
0$
#1885000000
1!
b11111111 #
1$
b11111111 &
b11111111 ,
#1890000000
0!
0$
#1895000000
1!
1$
b0001100000 '
b0100110001 (
b1010 )
b1010 -
b0100110001 .
#1900000000
0!
0$
#1905000000
1!
1$
b00000000 +
#1910000000
0!
0$
#1915000000
1!
b00000000 #
1$
b00000000 &
b00000000 ,
#1920000000
0!
0$
#1925000000
1!
1$
b0100110001 '
b1100000000 (
b1011 )
b1011 -
b1100000000 .
#1930000000
0!
0$
#1935000000
1!
1$
b00000001 +
#1940000000
0!
0$
#1945000000
1!
1$
b00000101 *
#1950000000
0!
0$
#1955000000
1!
1$
b1100000000 '
b1000001000 (
b1100 )
b1100 -
b1000001000 .
#1960000000
0!
0$
#1965000000
1!
1$
#1970000000
0!
0$
#1975000000
1!
1$
#1980000000
0!
0$
#1985000000
1!
1$
b1000001000 '
b0000000000 (
b1101 )
b1101 -
b0000000000 .
#1990000000
0!
0$
#1995000000
1!
1$
b0001110000 (
b1000 )
b1000 -
b0001110000 .
#2000000000
0!
0$
#2005000000
1!
1$
#2010000000
0!
0$
#2015000000
1!
1$
b0001110000 '
b0001100000 (
b1001 )
b1001 -
b0001100000 .
#2020000000
0!
0$
#2025000000
1!
1$
b11111111 +
#2030000000
0!
0$
#2035000000
1!
b11111111 #
1$
b11111111 &
b11111111 ,
#2040000000
0!
0$
#2045000000
1!
1$
b0001100000 '
b0100110001 (
b1010 )
b1010 -
b0100110001 .
#2050000000
0!
0$
#2055000000
1!
1$
b00000000 +
#2060000000
0!
0$
#2065000000
1!
b00000000 #
1$
b00000000 &
b00000000 ,
#2070000000
0!
0$
#2075000000
1!
1$
b0100110001 '
b1100000000 (
b1011 )
b1011 -
b1100000000 .
#2080000000
0!
0$
#2085000000
1!
1$
b00000001 +
#2090000000
0!
0$
#2095000000
1!
1$
b00000100 *
#2100000000
0!
0$
#2105000000
1!
1$
b1100000000 '
b1000001000 (
b1100 )
b1100 -
b1000001000 .
#2110000000
0!
0$
#2115000000
1!
1$
#2120000000
0!
0$
#2125000000
1!
1$
#2130000000
0!
0$
#2135000000
1!
1$
b1000001000 '
b0000000000 (
b1101 )
b1101 -
b0000000000 .
#2140000000
0!
0$
#2145000000
1!
1$
b0001110000 (
b1000 )
b1000 -
b0001110000 .
#2150000000
0!
0$
#2155000000
1!
1$
#2160000000
0!
0$
#2165000000
1!
1$
b0001110000 '
b0001100000 (
b1001 )
b1001 -
b0001100000 .
#2170000000
0!
0$
#2175000000
1!
1$
b11111111 +
#2180000000
0!
0$
#2185000000
1!
b11111111 #
1$
b11111111 &
b11111111 ,
#2190000000
0!
0$
#2195000000
1!
1$
b0001100000 '
b0100110001 (
b1010 )
b1010 -
b0100110001 .
#2200000000
0!
0$
#2205000000
1!
1$
b00000000 +
#2210000000
0!
0$
#2215000000
1!
b00000000 #
1$
b00000000 &
b00000000 ,
#2220000000
0!
0$
#2225000000
1!
1$
b0100110001 '
b1100000000 (
b1011 )
b1011 -
b1100000000 .
#2230000000
0!
0$
#2235000000
1!
1$
b00000001 +
#2240000000
0!
0$
#2245000000
1!
1$
b00000011 *
#2250000000
0!
0$
#2255000000
1!
1$
b1100000000 '
b1000001000 (
b1100 )
b1100 -
b1000001000 .
#2260000000
0!
0$
#2265000000
1!
1$
#2270000000
0!
0$
#2275000000
1!
1$
#2280000000
0!
0$
#2285000000
1!
1$
b1000001000 '
b0000000000 (
b1101 )
b1101 -
b0000000000 .
#2290000000
0!
0$
#2295000000
1!
1$
b0001110000 (
b1000 )
b1000 -
b0001110000 .
#2300000000
0!
0$
#2305000000
1!
1$
#2310000000
0!
0$
#2315000000
1!
1$
b0001110000 '
b0001100000 (
b1001 )
b1001 -
b0001100000 .
#2320000000
0!
0$
#2325000000
1!
1$
b11111111 +
#2330000000
0!
0$
#2335000000
1!
b11111111 #
1$
b11111111 &
b11111111 ,
#2340000000
0!
0$
#2345000000
1!
1$
b0001100000 '
b0100110001 (
b1010 )
b1010 -
b0100110001 .
#2350000000
0!
0$
#2355000000
1!
1$
b00000000 +
#2360000000
0!
0$
#2365000000
1!
b00000000 #
1$
b00000000 &
b00000000 ,
#2370000000
0!
0$
#2375000000
1!
1$
b0100110001 '
b1100000000 (
b1011 )
b1011 -
b1100000000 .
#2380000000
0!
0$
#2385000000
1!
1$
b00000001 +
#2390000000
0!
0$
#2395000000
1!
1$
b00000010 *
#2400000000
0!
0$
#2405000000
1!
1$
b1100000000 '
b1000001000 (
b1100 )
b1100 -
b1000001000 .
#2410000000
0!
0$
#2415000000
1!
1$
#2420000000
0!
0$
#2425000000
1!
1$
#2430000000
0!
0$
#2435000000
1!
1$
b1000001000 '
b0000000000 (
b1101 )
b1101 -
b0000000000 .
#2440000000
0!
0$
#2445000000
1!
1$
b0001110000 (
b1000 )
b1000 -
b0001110000 .
#2450000000
0!
0$
#2455000000
1!
1$
#2460000000
0!
0$
#2465000000
1!
1$
b0001110000 '
b0001100000 (
b1001 )
b1001 -
b0001100000 .
#2470000000
0!
0$
#2475000000
1!
1$
b11111111 +
#2480000000
0!
0$
#2485000000
1!
b11111111 #
1$
b11111111 &
b11111111 ,
#2490000000
0!
0$
#2495000000
1!
1$
b0001100000 '
b0100110001 (
b1010 )
b1010 -
b0100110001 .
#2500000000
0!
0$
#2505000000
1!
1$
b00000000 +
#2510000000
0!
0$
#2515000000
1!
b00000000 #
1$
b00000000 &
b00000000 ,
#2520000000
0!
0$
#2525000000
1!
1$
b0100110001 '
b1100000000 (
b1011 )
b1011 -
b1100000000 .
#2530000000
0!
0$
#2535000000
1!
1$
b00000001 +
#2540000000
0!
0$
#2545000000
1!
1$
b00000001 *
#2550000000
0!
0$
#2555000000
1!
1$
b1100000000 '
b1000001000 (
b1100 )
b1100 -
b1000001000 .
#2560000000
0!
0$
#2565000000
1!
1$
#2570000000
0!
0$
#2575000000
1!
1$
#2580000000
0!
0$
#2585000000
1!
1$
b1000001000 '
b0000000000 (
b1101 )
b1101 -
b0000000000 .
#2590000000
0!
0$
#2595000000
1!
1$
b0001110000 (
b1000 )
b1000 -
b0001110000 .
#2600000000
0!
0$
#2605000000
1!
1$
#2610000000
0!
0$
#2615000000
1!
1$
b0001110000 '
b0001100000 (
b1001 )
b1001 -
b0001100000 .
#2620000000
0!
0$
#2625000000
1!
1$
b11111111 +
#2630000000
0!
0$
#2635000000
1!
b11111111 #
1$
b11111111 &
b11111111 ,
#2640000000
0!
0$
#2645000000
1!
1$
b0001100000 '
b0100110001 (
b1010 )
b1010 -
b0100110001 .
#2650000000
0!
0$
#2655000000
1!
1$
b00000000 +
#2660000000
0!
0$
#2665000000
1!
b00000000 #
1$
b00000000 &
b00000000 ,
#2670000000
0!
0$
#2675000000
1!
1$
b0100110001 '
b1100000000 (
b1011 )
b1011 -
b1100000000 .
#2680000000
0!
0$
#2685000000
1!
1$
b00000001 +
#2690000000
0!
0$
#2695000000
1!
1$
b00000000 *
#2700000000
0!
0$
#2705000000
1!
1$
b1100000000 '
b1000001000 (
b1100 )
b1100 -
b1000001000 .
#2710000000
0!
0$
#2715000000
1!
1$
b0010100000 (
b0000 )
b0000 -
b0010100000 .
#2720000000
0!
0$
#2725000000
1!
1$
#2730000000
0!
0$
#2735000000
1!
1$
b0010100000 '
b0011100001 (
b0001 )
b0001 -
b0011100001 .
#2740000000
0!
0$
#2745000000
1!
1$
b00000000 +
#2750000000
0!
0$
#2755000000
1!
1$
#2760000000
0!
0$
#2765000000
1!
1$
b0011100001 '
b0001000000 (
b0010 )
b0010 -
b0001000000 .
#2770000000
0!
0$
#2775000000
1!
1$
b00000001 +
#2780000000
0!
0$
#2785000000
1!
1$
b00010000 *
#2790000000
0!
0$
