prime/prime.vhd
-- Copyright (C) 1991-2012 Altera Corporation
-- Your use of Altera Corporation's design tools, logic functions 
-- and other software and tools, and its AMPP partner logic 
-- functions, and any output files from any of the foregoing 
-- (including device programming or simulation files), and any 
-- associated documentation or information are expressly subject 
-- to the terms and conditions of the Altera Program License 
-- Subscription Agreement, Altera MegaCore Function License 
-- Agreement, or other applicable license agreement, including, 
-- without limitation, that your use is for the sole purpose of 
-- programming logic devices manufactured by Altera and sold by 
-- Altera or its authorized distributors.  Please refer to the 
-- applicable agreement for further details.

-- PROGRAM		"Quartus II 32-bit"
-- VERSION		"Version 12.1 Build 177 11/07/2012 SJ Full Version"
-- CREATED		"Tue Sep 19 22:23:22 2023"

LIBRARY ieee;
USE ieee.std_logic_1164.all; 

LIBRARY work;

ENTITY prime IS 
	PORT
	(
		A :  IN  STD_LOGIC;
		B :  IN  STD_LOGIC;
		C :  IN  STD_LOGIC;
		D :  IN  STD_LOGIC;
		O :  OUT  STD_LOGIC
	);
END prime;

ARCHITECTURE bdf_type OF prime IS 

SIGNAL	E :  STD_LOGIC;
SIGNAL	F :  STD_LOGIC;
SIGNAL	G :  STD_LOGIC;
SIGNAL	SYNTHESIZED_WIRE_0 :  STD_LOGIC;
SIGNAL	SYNTHESIZED_WIRE_1 :  STD_LOGIC;
SIGNAL	SYNTHESIZED_WIRE_2 :  STD_LOGIC;
SIGNAL	SYNTHESIZED_WIRE_3 :  STD_LOGIC;


BEGIN 



SYNTHESIZED_WIRE_0 <= E AND C AND D;


SYNTHESIZED_WIRE_3 <= E AND F AND C;


SYNTHESIZED_WIRE_1 <= B AND G AND D;


SYNTHESIZED_WIRE_2 <= F AND C AND D;


O <= SYNTHESIZED_WIRE_0 OR SYNTHESIZED_WIRE_1 OR SYNTHESIZED_WIRE_2 OR SYNTHESIZED_WIRE_3;


E <= NOT(A);



F <= NOT(B);



G <= NOT(C);



END bdf_type;

prime/primetb.vhd
library ieee;
use ieee.std_logic_1164.all;

entity primetb is
end primetb;

architecture one of primetb is

  signal a, b, c, d, o: std_logic;

  component prime
  port( 
    A :  IN  STD_LOGIC;
    B :  IN  STD_LOGIC;
    C :  IN  STD_LOGIC;
    D :  IN  STD_LOGIC;
    O :  OUT  STD_LOGIC
    );
  end component;

begin

  A <= '0', '1' after 200 ns, '0' after 400 ns;
  B <= '0', '1' after 100 ns, '0' after 200 ns, '1' after 300 ns, '0' after 400 ns;
  C <= '0', '1' after 50 ns, '0' after 100 ns, '1' after 150 ns, '0' after 200 ns, '1' after 250 ns, '0' after 300 ns, '1' after 350 ns;
  D <= '0', '1' after 25 ns, '0' after 50 ns, '1' after 75 ns, '0' after 100 ns, '1' after 125 ns, '0' after 150 ns, '1' after 175 ns, '0' after 200 ns, '1' after 225 ns, '0' after 250 ns, '1' after 275 ns, '0' after 300 ns, '1' after 325 ns, '0' after 350 ns, '1' after 375 ns, '0' after 400 ns;

  T0: prime port map(A, B, C, D, O);

end one;

prime/primetb.vcd
$date
  Sun Sep 24 21:07:55 2023
$end
$version
  GHDL v0
$end
$timescale
  1 fs
$end
$scope module standard $end
$upscope $end
$scope module std_logic_1164 $end
$upscope $end
$scope module primetb $end
$var reg 1 ! a $end
$var reg 1 " b $end
$var reg 1 # c $end
$var reg 1 $ d $end
$var reg 1 % o $end
$scope module t0 $end
$var reg 1 & a $end
$var reg 1 ' b $end
$var reg 1 ( c $end
$var reg 1 ) d $end
$var reg 1 * o $end
$var reg 1 + e $end
$var reg 1 , f $end
$var reg 1 - g $end
$var reg 1 . synthesized_wire_0 $end
$var reg 1 / synthesized_wire_1 $end
$var reg 1 0 synthesized_wire_2 $end
$var reg 1 1 synthesized_wire_3 $end
$upscope $end
$upscope $end
$enddefinitions $end
#0
0!
0"
0#
0$
0%
0&
0'
0(
0)
0*
1+
1,
1-
0.
0/
00
01
#25000000
1$
1)
#50000000
1#
0$
1%
1(
0)
1*
0-
11
#75000000
1$
1)
1.
10
#100000000
1"
0#
0$
0%
1'
0(
0)
0*
0,
1-
0.
00
01
#125000000
1$
1%
1)
1*
1/
#150000000
1#
0$
0%
1(
0)
0*
0-
0/
#175000000
1$
1%
1)
1*
1.
#200000000
1!
0"
0#
0$
0%
1&
0'
0(
0)
0*
0+
1,
1-
0.
#225000000
1$
1)
#250000000
1#
0$
1(
0)
0-
#275000000
1$
1%
1)
1*
10
#300000000
1"
0#
0$
0%
1'
0(
0)
0*
0,
1-
00
#325000000
1$
1%
1)
1*
1/
#350000000
1#
0$
0%
1(
0)
0*
0-
0/
#375000000
1$
1)
#400000000
0!
0"
0$
1%
0&
0'
0)
1*
1+
1,
11
