project3/bright/bright.vhd
-- Quartus II VHDL Template
-- Four-State Moore State Machine

-- A Moore machine's outputs are dependent only on the current state.
-- The output is written only when the state changes.  (State
-- transitions are synchronous.)

library ieee;
use ieee.std_logic_1164.all;

entity bright is

	port(
		clk		 : in	std_logic;
		buttonOne : in std_logic;
		buttonTwo : in std_logic;
		buttonThree : in std_logic;
		reset	 : in	std_logic;
		greenLed	 : out	std_logic_vector(3 downto 0)
	);

end entity;

architecture rtl of bright is

	-- Build an enumerated type for the state machine
	type state_type is (sIdle, sOne, sTwo, sThree);

	-- Register to hold the current state
	signal state   : state_type;

begin

    process (clk, reset)
    begin
        if reset = '0' then
            state <= sIdle;
        elsif (rising_edge(clk)) then
            case state is
                when sIdle=>
                    if buttonOne = '0' then
                        state <= sOne;
                    end if;
                when sOne=>
                    if buttonTwo = '0' then
                        state <= sTwo;
                    elsif buttonThree = '0' then
                        state <= sIdle;
                    end if;
                when sTwo=>
                    if buttonThree = '0' then
                        state <= sThree;
                    elsif buttonOne = '0' then
                        state <= sIdle;
                    end if;
                when sThree =>
                    if buttonOne = '0' or buttonTwo = '0' then
                        state <= sIdle;
                    end if;
            end case;
        end if;
    end process;

    process (state)
    begin
        case state is
            when sIdle =>
                greenLed <= "0001"; -- green LED 0 is active
            when sOne =>
                greenLed <= "0010"; -- green LED 1 is active
            when sTwo =>
                greenLed <= "0100"; -- green LED 2 is active
            when sThree =>
                greenLed <= "1000"; -- green LED 9 is active, assuming bit 0 represents green LED 9
        end case;
    end process;

end rtl;

project3/bright/brighttest.vhd
-- Bruce A. Maxwell
-- Spring 2013
-- CS 232 Lab 3
-- Test bench for the bright state machine circuit
--

library ieee;
use ieee.std_logic_1164.all;

-- a test bench has no inputs or outputs
entity brighttest is
end brighttest;

-- architecture
architecture test of brighttest is

  -- internal signals for everything we want to send to or receive from the
  -- test circuit
  signal Reset, P1, P2, P3: std_logic;
  signal gled: std_logic_vector (3 downto 0);

  -- the component statement lets us instantiate a bright circuit
  component bright
    port(
      clk		 : in	std_logic;
      buttonOne	 : in	std_logic;
      buttonTwo	: in std_logic;
      buttonThree	: in std_logic;
      reset	 : in	std_logic;
      greenLed	 : out	std_logic_vector(3 downto 0)
      );
  end component;

  -- signals for making the clock
  constant num_cycles : integer := 20;
  signal clk : std_logic := '1';

begin

  -- these are timed signal assignments to create specific patterns
  Reset <= '0', '1' after 7 ns;
  P1 <= '1', '0' after 20 ns, '1' after 35 ns, '0' after 105 ns, '1' after 125 ns,
      '0' after 155 ns, '1' after 165 ns;
  P2 <= '1', '0' after 45 ns, '1' after 65 ns, '0' after 135 ns, '1' after 145 ns;
  P3 <= '1', '0' after 75 ns, '1' after 90 ns;
  

  -- we can use a process and a for loop to generate a clock signal
  process begin
    for i in 1 to num_cycles loop
      clk <= not clk;
      wait for 5 ns;
      clk <= not clk;
      wait for 5 ns;
    end loop;
    wait;
  end process;

  -- this instantiates a bright circuit and sets up the inputs and outputs
  B0: bright port map (clk, P1, P2, P3, reset, gled);
end test;

project3/bright/brighttest.vcd
$date
  Mon Oct  2 11:59:06 2023
$end
$version
  GHDL v0
$end
$timescale
  1 fs
$end
$scope module standard $end
$upscope $end
$scope module std_logic_1164 $end
$upscope $end
$scope module brighttest $end
$var reg 1 ! reset $end
$var reg 1 " p1 $end
$var reg 1 # p2 $end
$var reg 1 $ p3 $end
$var reg 4 % gled[3:0] $end
$var reg 1 & clk $end
$scope module b0 $end
$var reg 1 ' clk $end
$var reg 1 ( buttonone $end
$var reg 1 ) buttontwo $end
$var reg 1 * buttonthree $end
$var reg 1 + reset $end
$var reg 4 , greenled[3:0] $end
$comment state is not handled $end
$upscope $end
$upscope $end
$enddefinitions $end
#0
0!
1"
1#
1$
b0001 %
0&
0'
1(
1)
1*
0+
b0001 ,
#5000000
1&
1'
#7000000
1!
1+
#10000000
0&
0'
#15000000
1&
1'
#20000000
0"
0&
0'
0(
#25000000
b0010 %
1&
1'
b0010 ,
#30000000
0&
0'
#35000000
1"
1&
1'
1(
#40000000
0&
0'
#45000000
0#
b0100 %
1&
1'
0)
b0100 ,
#50000000
0&
0'
#55000000
1&
1'
#60000000
0&
0'
#65000000
1#
1&
1'
1)
#70000000
0&
0'
#75000000
0$
b1000 %
1&
1'
0*
b1000 ,
#80000000
0&
0'
#85000000
1&
1'
#90000000
1$
0&
0'
1*
#95000000
1&
1'
#100000000
0&
0'
#105000000
0"
b0001 %
1&
1'
0(
b0001 ,
#110000000
0&
0'
#115000000
b0010 %
1&
1'
b0010 ,
#120000000
0&
0'
#125000000
1"
1&
1'
1(
#130000000
0&
0'
#135000000
0#
b0100 %
1&
1'
0)
b0100 ,
#140000000
0&
0'
#145000000
1#
1&
1'
1)
#150000000
0&
0'
#155000000
0"
b0001 %
1&
1'
0(
b0001 ,
#160000000
0&
0'
#165000000
1"
1&
1'
1(
