flash/hexdisplay.vhd
library ieee;
use ieee.std_logic_1164.all;
use ieee.numeric_std.all;

entity hexdisplay is
    port 
    (
        a	    : in UNSIGNED (3 downto 0);
        segments : out UNSIGNED (6 downto 0)
    );
end entity;

architecture rtl of hexdisplay is
begin
    process(a)
    begin
        case a is
				-- Extension: Exploring case/switch-case in VHDL
            when "0000" => segments <= "0011111"; -- 0
            when "0001" => segments <= "0000011"; -- 1
            when "0010" => segments <= "0101101"; -- 2
            when "0011" => segments <= "0100111"; -- 3
            when "0100" => segments <= "0110011"; -- 4
            when "0101" => segments <= "0110110"; -- 5
            when "0110" => segments <= "0111110"; -- 6
            when "0111" => segments <= "0000011"; -- 7
            when "1000" => segments <= "0111111"; -- 8
            when "1001" => segments <= "0110111"; -- 9
            when "1010" => segments <= "0111011"; -- A
            when "1011" => segments <= "0011110"; -- b
            when "1100" => segments <= "0011100"; -- C
            when "1101" => segments <= "0101111"; -- d
            when "1110" => segments <= "0111100"; -- E
            when "1111" => segments <= "0111000"; -- F
            when others => segments <= "0000000"; -- Off for undefined inputs
        end case;
    end process;
end rtl;

Project2/boxtest.vhd
library ieee;
use ieee.std_logic_1164.all;
use ieee.numeric_std.all;

entity boxtest is
end entity;

architecture test of boxtest is
    signal A: UNSIGNED(3 downto 0);
    signal segments: UNSIGNED(6 downto 0);

    component hexdisplay
        port(
            a        : in UNSIGNED(3 downto 0);
            segments : out UNSIGNED(6 downto 0)
        );
    end component;
    
begin

    A <= "0000", "0001" after 200 ns, "0010" after 400 ns, "0011" after 600 ns, "0100" after 800 ns, "0101" after 1000 ns, "0110" after 1200 ns, "0111" after 1400 ns, "1000" after 1600 ns, "1001" after 1800 ns, "1010" after 2000 ns, "1011" after 2200 ns, "1100" after 2400 ns, "1101" after 2600 ns, "1110" after 2800 ns, "1111" after 3000 ns;

    C0: hexdisplay port map( A => a, segments => segments );
	 
end test;

Project2/boxtest.vcd
$date
  Thu Sep 28 22:55:28 2023
$end
$version
  GHDL v0
$end
$timescale
  1 fs
$end
$scope module standard $end
$upscope $end
$scope module std_logic_1164 $end
$upscope $end
$scope module numeric_std $end
$upscope $end
$scope module boxtest $end
$var reg 4 ! a[3:0] $end
$var reg 7 " segments[6:0] $end
$scope module c0 $end
$var reg 4 # a[3:0] $end
$var reg 7 $ segments[6:0] $end
$upscope $end
$upscope $end
$enddefinitions $end
#0
b0000 !
b0000001 "
b0000 #
b0000001 $
#200000000
b0001 !
b1111001 "
b0001 #
b1111001 $
#400000000
b0010 !
b0100101 "
b0010 #
b0100101 $
#600000000
b0011 !
b0110001 "
b0011 #
b0110001 $
#800000000
b0100 !
b0011001 "
b0100 #
b0011001 $
#1000000000
b0101 !
b0010010 "
b0101 #
b0010010 $
#1200000000
b0110 !
b0000010 "
b0110 #
b0000010 $
#1400000000
b0111 !
b1111000 "
b0111 #
b1111000 $
#1600000000
b1000 !
b0000000 "
b1000 #
b0000000 $
#1800000000
b1001 !
b0010000 "
b1001 #
b0010000 $
#2000000000
b1010 !
b0001000 "
b1010 #
b0001000 $
#2200000000
b1011 !
b0000110 "
b1011 #
b0000110 $
#2400000000
b1100 !
b0100111 "
b1100 #
b0100111 $
#2600000000
b1101 !
b0100001 "
b1101 #
b0100001 $
#2800000000
b1110 !
b0000111 "
b1110 #
b0000111 $
#3000000000
b1111 !
b0001111 "
b1111 #
b0001111 $
