lab1/lab1.vhd
-- Copyright (C) 1991-2012 Altera Corporation
-- Your use of Altera Corporation's design tools, logic functions 
-- and other software and tools, and its AMPP partner logic 
-- functions, and any output files from any of the foregoing 
-- (including device programming or simulation files), and any 
-- associated documentation or information are expressly subject 
-- to the terms and conditions of the Altera Program License 
-- Subscription Agreement, Altera MegaCore Function License 
-- Agreement, or other applicable license agreement, including, 
-- without limitation, that your use is for the sole purpose of 
-- programming logic devices manufactured by Altera and sold by 
-- Altera or its authorized distributors.  Please refer to the 
-- applicable agreement for further details.

-- PROGRAM		"Quartus II 32-bit"
-- VERSION		"Version 12.1 Build 177 11/07/2012 SJ Full Version"
-- CREATED		"Mon Sep 11 15:07:22 2023"

LIBRARY ieee;
USE ieee.std_logic_1164.all; 

LIBRARY work;

ENTITY lab1 IS 
	PORT
	(
		A :  IN  STD_LOGIC;
		B :  IN  STD_LOGIC;
		F :  OUT  STD_LOGIC
	);
END lab1;

ARCHITECTURE bdf_type OF lab1 IS 

SIGNAL	SYNTHESIZED_WIRE_0 :  STD_LOGIC;
SIGNAL	SYNTHESIZED_WIRE_1 :  STD_LOGIC;
SIGNAL	SYNTHESIZED_WIRE_2 :  STD_LOGIC;
SIGNAL	SYNTHESIZED_WIRE_3 :  STD_LOGIC;


BEGIN 



SYNTHESIZED_WIRE_3 <= A AND B;


SYNTHESIZED_WIRE_2 <= SYNTHESIZED_WIRE_0 AND SYNTHESIZED_WIRE_1;


F <= SYNTHESIZED_WIRE_2 OR SYNTHESIZED_WIRE_3;


SYNTHESIZED_WIRE_0 <= NOT(A);



SYNTHESIZED_WIRE_1 <= NOT(B);



END bdf_type;

lab1/testbench.vhd
-- Stephanie Taylor
-- Fall 2020
-- CS 232 Lab 1
-- Test file for the simple circuit in lab 1

library ieee;
use ieee.std_logic_1164.all;

entity testbench is
end testbench;

architecture one of testbench is

  signal a, b, f: std_logic;

  component lab1
  port( 
    A :  IN  STD_LOGIC;
    B :  IN  STD_LOGIC;
    F :  OUT  STD_LOGIC
    );
  end component;

begin

A <= '0', '1' after 75 ns, '0' after 100 ns, '1' after 150 ns, '0' after 175 ns;
B <= '0', '1' after 25 ns, '0' after 50 ns, '1' after 125 ns;

T0: lab1 port map(A, B, F);

end one;

lab1/testbench.vcd
$date
  Mon Sep 11 15:07:48 2023
$end
$version
  GHDL v0
$end
$timescale
  1 fs
$end
$scope module standard $end
$upscope $end
$scope module std_logic_1164 $end
$upscope $end
$scope module testbench $end
$var reg 1 ! a $end
$var reg 1 " b $end
$var reg 1 # f $end
$scope module t0 $end
$var reg 1 $ a $end
$var reg 1 % b $end
$var reg 1 & f $end
$var reg 1 ' synthesized_wire_0 $end
$var reg 1 ( synthesized_wire_1 $end
$var reg 1 ) synthesized_wire_2 $end
$var reg 1 * synthesized_wire_3 $end
$upscope $end
$upscope $end
$enddefinitions $end
#0
0!
0"
1#
0$
0%
1&
1'
1(
1)
0*
#25000000
1"
0#
1%
0&
0(
0)
#50000000
0"
1#
0%
1&
1(
1)
#75000000
1!
0#
1$
0&
0'
0)
#100000000
0!
1#
0$
1&
1'
1)
#125000000
1"
0#
1%
0&
0(
0)
#150000000
1!
1#
1$
1&
0'
1*
#175000000
0!
0#
0$
0&
1'
0*
