project8/alu.vhd
-- Parth Parth
-- CS 232 Fall 2023

LIBRARY ieee;
USE ieee.std_logic_1164.ALL;
USE ieee.numeric_std.ALL;

ENTITY alu IS
  PORT (
    srcA : IN unsigned(15 DOWNTO 0); -- input A
    srcB : IN unsigned(15 DOWNTO 0); -- input B
    op : IN STD_LOGIC_VECTOR(2 DOWNTO 0); -- operation
    cr : OUT STD_LOGIC_VECTOR(3 DOWNTO 0); -- condition outputs
    dest : OUT unsigned(15 DOWNTO 0) -- output value
  );
END alu;

ARCHITECTURE test OF alu IS
  -- The signal tdest is an intermediate signal to hold the result and
  -- catch the carry bit in location 16.
  SIGNAL tdest : unsigned(16 DOWNTO 0);

BEGIN -- test
  PROCESS (srcA, srcB, op)
  BEGIN -- process
    CASE op IS
      WHEN "000" => -- addition     tdest = srcA + srcB
        tdest <= ('0' & srcA) + srcB;
      WHEN "001" => -- subtraction  tdest = srcA - srcB
        tdest <= ('0' & srcA) - srcB;
      WHEN "010" => -- and          tdest = srcA and srcB
        tdest <= '0' & unsigned(STD_LOGIC_VECTOR(srcA) AND STD_LOGIC_VECTOR(srcB));
      WHEN "011" => -- or           tdest = srcA or srcB
        tdest <= '0' & unsigned(STD_LOGIC_VECTOR(srcA) OR STD_LOGIC_VECTOR(srcB));
      WHEN "100" => -- xor          tdest = srcA xor srcB
        tdest <= '0' & unsigned(STD_LOGIC_VECTOR(srcA) XOR STD_LOGIC_VECTOR(srcB));

      WHEN "101" => -- shift        tdest = srcA shifted left arithmetic by one if srcB(0) is 0, otherwise right
        -- shift and preserve sign  
        IF srcB(0) = '0' THEN
          tdest <= srcA(15 DOWNTO 0) & '0';
        ELSE
          tdest <= '0' & srcA(15) & srcA(15 DOWNTO 1);
        END IF;

      WHEN "110" => -- rotate       tdest = srcA rotated left by one if srcB(0) is 0, otherwise right
        IF srcB(0) = '0' THEN
          tdest <= srcA(15 DOWNTO 0) & srcA(15);
        ELSE
          tdest <= '0' & srcA(0) & srcA(15 DOWNTO 1);
        END IF;

      WHEN "111" => -- pass         tdest = srcA
        tdest <= '0' & srcA;
      WHEN OTHERS =>
        NULL;
    END CASE;
  END PROCESS;

  -- connect the low 16 bits of tdest to dest here
  dest <= tdest(15 DOWNTO 0);

  -- set the four CR output bits here
  -- cr(0) <= '1' if the result of the operation is 0
  cr(0) <= '1' WHEN tdest(15 DOWNTO 0) = "0000000000000000" ELSE
  '0';
  -- cr(1) <= '1' if there is a 2's complement overflow
  cr(1) <= '1' WHEN srcA(15) = srcB(15) AND srcA(15) /= tdest(15) AND (op = "000" OR op = "001") ELSE
  '0';
  -- cr(2) <= '1' if the result of the operation is negative
  cr(2) <= '1' WHEN tdest(15) = '1' ELSE
  '0';
  -- cr(3) <= '1' if the operation generated a carry of '1'
  cr(3) <= '1' WHEN tdest(16) = '1' ELSE
  '0';

END test;

project7/cpu/alutestbench.vhd
LIBRARY ieee;
USE ieee.std_logic_1164.ALL;
USE ieee.numeric_std.ALL;

ENTITY alutestbench IS
END alutestbench;

ARCHITECTURE test OF alutestbench IS
  CONSTANT num_cycles : INTEGER := 20;
  SIGNAL state : unsigned(3 DOWNTO 0);
  SIGNAL srcA : unsigned(15 DOWNTO 0);
  SIGNAL srcB : unsigned(15 DOWNTO 0);
  SIGNAL dest : unsigned(15 DOWNTO 0) := "0000000000000000";
  SIGNAL opcode : STD_LOGIC_VECTOR(2 DOWNTO 0);

  SIGNAL output : STD_LOGIC_VECTOR(15 DOWNTO 0) := "0000000000000000";
  SIGNAL CR : STD_LOGIC_VECTOR(3 DOWNTO 0) := "0000";
  SIGNAL clk : STD_LOGIC := '1';
  SIGNAL reset : STD_LOGIC;

  -- component statement for the ALU
  COMPONENT alu
    PORT (
      srcA : IN unsigned(15 DOWNTO 0); -- input A
      srcB : IN unsigned(15 DOWNTO 0); -- input B
      op : IN STD_LOGIC_VECTOR(2 DOWNTO 0); -- operation
      cr : OUT STD_LOGIC_VECTOR(3 DOWNTO 0); -- condition outputs
      dest : OUT unsigned(15 DOWNTO 0)); -- output value
  END COMPONENT;

BEGIN

  -- start off with a short reset
  reset <= '0', '1' AFTER 1 ns;

  -- create a clock
  PROCESS
  BEGIN
    FOR i IN 1 TO num_cycles LOOP
      clk <= NOT clk;
      WAIT FOR 1 ns;
      clk <= NOT clk;
      WAIT FOR 1 ns;
    END LOOP;
    WAIT;
  END PROCESS;
  aluinstance : alu
  PORT MAP(srcA => srcA, srcB => srcB, dest => dest, op => opcode, cr => CR);

  output <= STD_LOGIC_VECTOR(dest); -- connect dest and the output

  PROCESS (clk, reset)
  BEGIN
    IF reset = '0' THEN
      srcA <= "0000000000000000";
      srcB <= "0000000000000000";
      state <= "0000";
    ELSIF rising_edge(clk) THEN
      CASE state IS
        WHEN "0000" =>
          srcA <= x"7FFF";
          srcB <= x"0002";
          opcode <= "000"; -- addition, answer should be x8001, flags "0110"
          state <= state + 1;
        WHEN "0001" =>
          srcA <= x"FF10";
          srcB <= x"FFFF";
          opcode <= "000"; -- addition, answer should be xFF0F, flags "1100"
          state <= state + 1;
        WHEN "0010" =>
          srcA <= x"0014";
          srcB <= x"0012";
          opcode <= "001"; -- subtraction, answer should be x0002, flags "0000"
          state <= state + 1;
        WHEN "0011" =>
          srcA <= x"FFFE";
          srcB <= x"FFFF";
          opcode <= "001"; -- subtraction, answer should be xFFFF, flags "1100"
          state <= state + 1;
        WHEN "0100" =>
          srcA <= x"FFFF";
          srcB <= x"AAAA";
          opcode <= "010"; -- and, answer should be xAAAA, flags "0100"
          state <= state + 1;
        WHEN "0101" =>
          srcA <= x"00FF";
          srcB <= x"AAAA"; -- and, answer should be x00AA, flags "0000"
          opcode <= "010";
          state <= state + 1;
        WHEN "0110" =>
          srcA <= x"FFFF";
          srcB <= x"AAAA";
          opcode <= "011"; -- or, answer should be xFFFF, flags "0100"
          state <= state + 1;
        WHEN "0111" =>
          srcA <= x"FF00";
          srcB <= x"AAAA"; -- or, answer should be xFFAA, flags "0100"
          opcode <= "011";
          state <= state + 1;
        WHEN "1000" =>
          srcA <= x"FFFF";
          srcB <= x"AAAA";
          opcode <= "100"; -- xor, answer should be x5555, flags "0000"
          state <= state + 1;
        WHEN "1001" =>
          srcA <= x"FF00";
          srcB <= x"AAAA";
          opcode <= "100"; -- xor, answer should be x55AA, flags "0000"
          state <= state + 1;
        WHEN "1010" =>
          srcA <= x"AAAA";
          srcB <= x"0000";
          opcode <= "101"; -- shift, left by 1, answer should be x5554, flags "1000"
          state <= state + 1;
        WHEN "1011" =>
          srcA <= x"AAAA";
          srcB <= x"0001";
          opcode <= "101"; -- shift, right by 1, answer should be xD555, flags "0100"
          state <= state + 1;
        WHEN "1100" =>
          srcA <= x"AAAA";
          srcB <= x"0000";
          opcode <= "110"; -- rotate, left by 1, answer should be x5555, flags "1000"
          state <= state + 1;
        WHEN "1101" =>
          srcA <= x"AAAA";
          srcB <= x"0001";
          opcode <= "110"; -- rotate, right by 1, answer should be x5555, flags "0000"
          state <= state + 1;
        WHEN "1110" =>
          srcA <= x"0000";
          srcB <= x"0234";
          opcode <= "111"; -- pass through, answer should be x0000, flags "0001"
          state <= state + 1;
        WHEN OTHERS =>
          srcA <= x"F012";
          srcB <= x"0000";
          opcode <= "111"; -- pass through, answer should be xF012, flags "0100"
          state <= state + 1;
      END CASE;
    END IF;
  END PROCESS;

END test;

project7/cpu/alutestbench.vcd
$date
  Mon Nov 27 22:27:56 2023
$end
$version
  GHDL v0
$end
$timescale
  1 fs
$end
$scope module standard $end
$upscope $end
$scope module std_logic_1164 $end
$upscope $end
$scope module numeric_std $end
$upscope $end
$scope module alutestbench $end
$var reg 4 ! state[3:0] $end
$var reg 16 " srca[15:0] $end
$var reg 16 # srcb[15:0] $end
$var reg 16 $ dest[15:0] $end
$var reg 3 % opcode[2:0] $end
$var reg 16 & output[15:0] $end
$var reg 4 ' cr[3:0] $end
$var reg 1 ( clk $end
$var reg 1 ) reset $end
$scope module aluinstance $end
$var reg 16 * srca[15:0] $end
$var reg 16 + srcb[15:0] $end
$var reg 3 , op[2:0] $end
$var reg 4 - cr[3:0] $end
$var reg 16 . dest[15:0] $end
$var reg 17 / tdest[16:0] $end
$upscope $end
$upscope $end
$enddefinitions $end
#0
b0000 !
b0000000000000000 "
b0000000000000000 #
bUUUUUUUUUUUUUUUU $
bUUU %
bUUUUUUUUUUUUUUUU &
b0000 '
0(
0)
b0000000000000000 *
b0000000000000000 +
bUUU ,
b0000 -
bUUUUUUUUUUUUUUUU .
bUUUUUUUUUUUUUUUUU /
#1000000
b0001 !
b0111111111111111 "
b0000000000000010 #
b1000000000000001 $
b000 %
b1000000000000001 &
b0110 '
1(
1)
b0111111111111111 *
b0000000000000010 +
b000 ,
b0110 -
b1000000000000001 .
b01000000000000001 /
#2000000
0(
#3000000
b0010 !
b1111111100010000 "
b1111111111111111 #
b1111111100001111 $
b1111111100001111 &
b1100 '
1(
b1111111100010000 *
b1111111111111111 +
b1100 -
b1111111100001111 .
b11111111100001111 /
#4000000
0(
#5000000
b0011 !
b0000000000010100 "
b0000000000010010 #
b0000000000000010 $
b001 %
b0000000000000010 &
b0000 '
1(
b0000000000010100 *
b0000000000010010 +
b001 ,
b0000 -
b0000000000000010 .
b00000000000000010 /
#6000000
0(
#7000000
b0100 !
b1111111111111110 "
b1111111111111111 #
b1111111111111111 $
b1111111111111111 &
b1100 '
1(
b1111111111111110 *
b1111111111111111 +
b1100 -
b1111111111111111 .
b11111111111111111 /
#8000000
0(
#9000000
b0101 !
b1111111111111111 "
b1010101010101010 #
b1010101010101010 $
b010 %
b1010101010101010 &
b0100 '
1(
b1111111111111111 *
b1010101010101010 +
b010 ,
b0100 -
b1010101010101010 .
b01010101010101010 /
#10000000
0(
#11000000
b0110 !
b0000000011111111 "
b0000000010101010 $
b0000000010101010 &
b0000 '
1(
b0000000011111111 *
b0000 -
b0000000010101010 .
b00000000010101010 /
#12000000
0(
#13000000
b0111 !
b1111111111111111 "
b1111111111111111 $
b011 %
b1111111111111111 &
b0100 '
1(
b1111111111111111 *
b011 ,
b0100 -
b1111111111111111 .
b01111111111111111 /
#14000000
0(
#15000000
b1000 !
b1111111100000000 "
b1111111110101010 $
b1111111110101010 &
1(
b1111111100000000 *
b1111111110101010 .
b01111111110101010 /
#16000000
0(
#17000000
b1001 !
b1111111111111111 "
b0101010101010101 $
b100 %
b0101010101010101 &
b0000 '
1(
b1111111111111111 *
b100 ,
b0000 -
b0101010101010101 .
b00101010101010101 /
#18000000
0(
#19000000
b1010 !
b1111111100000000 "
b0101010110101010 $
b0101010110101010 &
1(
b1111111100000000 *
b0101010110101010 .
b00101010110101010 /
#20000000
0(
#21000000
b1011 !
b1010101010101010 "
b0000000000000000 #
b0101010101010100 $
b101 %
b0101010101010100 &
b1000 '
1(
b1010101010101010 *
b0000000000000000 +
b101 ,
b1000 -
b0101010101010100 .
b10101010101010100 /
#22000000
0(
#23000000
b1100 !
b0000000000000001 #
b1101010101010101 $
b1101010101010101 &
b0100 '
1(
b0000000000000001 +
b0100 -
b1101010101010101 .
b01101010101010101 /
#24000000
0(
#25000000
b1101 !
b0000000000000000 #
b0101010101010101 $
b110 %
b0101010101010101 &
b1000 '
1(
b0000000000000000 +
b110 ,
b1000 -
b0101010101010101 .
b10101010101010101 /
#26000000
0(
#27000000
b1110 !
b0000000000000001 #
b0000 '
1(
b0000000000000001 +
b0000 -
b00101010101010101 /
#28000000
0(
#29000000
b1111 !
b0000000000000000 "
b0000001000110100 #
b0000000000000000 $
b111 %
b0000000000000000 &
b0001 '
1(
b0000000000000000 *
b0000001000110100 +
b111 ,
b0001 -
b0000000000000000 .
b00000000000000000 /
#30000000
0(
#31000000
b0000 !
b1111000000010010 "
b0000000000000000 #
b1111000000010010 $
b1111000000010010 &
b0100 '
1(
b1111000000010010 *
b0000000000000000 +
b0100 -
b1111000000010010 .
b01111000000010010 /
#32000000
0(
#33000000
b0001 !
b0111111111111111 "
b0000000000000010 #
b1000000000000001 $
b000 %
b1000000000000001 &
b0110 '
1(
b0111111111111111 *
b0000000000000010 +
b000 ,
b0110 -
b1000000000000001 .
b01000000000000001 /
#34000000
0(
#35000000
b0010 !
b1111111100010000 "
b1111111111111111 #
b1111111100001111 $
b1111111100001111 &
b1100 '
1(
b1111111100010000 *
b1111111111111111 +
b1100 -
b1111111100001111 .
b11111111100001111 /
#36000000
0(
#37000000
b0011 !
b0000000000010100 "
b0000000000010010 #
b0000000000000010 $
b001 %
b0000000000000010 &
b0000 '
1(
b0000000000010100 *
b0000000000010010 +
b001 ,
b0000 -
b0000000000000010 .
b00000000000000010 /
#38000000
0(
#39000000
b0100 !
b1111111111111110 "
b1111111111111111 #
b1111111111111111 $
b1111111111111111 &
b1100 '
1(
b1111111111111110 *
b1111111111111111 +
b1100 -
b1111111111111111 .
b11111111111111111 /
