flash/hexdisplay.vhd
library ieee;
use ieee.std_logic_1164.all;
use ieee.numeric_std.all;

entity hexdisplay is
    port 
    (
        a	    : in UNSIGNED (3 downto 0);
        segments : out UNSIGNED (6 downto 0)
    );
end entity;

architecture rtl of hexdisplay is
begin
    process(a)
    begin
        case a is
				-- Extension: Exploring case/switch-case in VHDL
            when "0000" => segments <= "0011111"; -- 0
            when "0001" => segments <= "0000011"; -- 1
            when "0010" => segments <= "0101101"; -- 2
            when "0011" => segments <= "0100111"; -- 3
            when "0100" => segments <= "0110011"; -- 4
            when "0101" => segments <= "0110110"; -- 5
            when "0110" => segments <= "0111110"; -- 6
            when "0111" => segments <= "0000011"; -- 7
            when "1000" => segments <= "0111111"; -- 8
            when "1001" => segments <= "0110111"; -- 9
            when "1010" => segments <= "0111011"; -- A
            when "1011" => segments <= "0011110"; -- b
            when "1100" => segments <= "0011100"; -- C
            when "1101" => segments <= "0101111"; -- d
            when "1110" => segments <= "0111100"; -- E
            when "1111" => segments <= "0111000"; -- F
            when others => segments <= "0000000"; -- Off for undefined inputs
        end case;
    end process;
end rtl;

project3/reaction/timer.vhd
library ieee;
use ieee.std_logic_1164.all;
use ieee.numeric_std.all;

entity timer is
    port (
        clk : in std_logic;
        reset : in std_logic;
        start : in std_logic;
        react : in std_logic;
        cycles : out std_logic_vector(7 downto 0);
        leds : out std_logic_vector(2 downto 0);
        curstate: out std_logic_vector(1 downto 0)
    );
end entity timer;

architecture rtl of timer is
    type state_type is (sIdle, sWait, sCount);

    signal count: unsigned(7 downto 0) := (others => '0');
    signal internal_state: state_type := sIdle;

begin
    process (clk, reset)
    begin
        if reset = '0' then
            count <= (others => '0');
            internal_state <= sIdle;
        elsif (rising_edge(clk)) then
            case internal_state is
                when sIdle =>
                    if start = '0' then
                        internal_state <= sWait;
                    end if;
                when sWait =>
                    if react = '0' then
                        count <= (others => '1');
                        internal_state <= sIdle;
                    elsif count = "00000011" then
                        count <= (others => '0');
                        internal_state <= sCount;
                    else
                        count <= count + 1;
                        internal_state <= sWait;
                    end if;
                when sCount =>
                    if react = '0' then
                        internal_state <= sIdle;
                    else
                        count <= count + 1;
                        internal_state <= sCount;
                    end if;
            end case;
        end if;

        case internal_state is
            when sIdle =>
                leds <= "100";
                cycles <= std_logic_vector(count(7 downto 0));
                curstate <= "00";
            when sWait =>
                leds <= "010";
                cycles <= "00000000";
                curstate <= "01";
            when sCount =>
                if react = '0' then
                    internal_state <= sIdle;
                else
                    count <= count + 1;
                end if;
                leds <= "001";
                cycles <= std_logic_vector(count(7 downto 0));
                curstate <= "10";
        end case;
    end process;
end rtl;

project3/reaction/timingtest.vhd
-- timingtest.vhd
-- Testbench for timer state machine

library ieee;
use ieee.std_logic_1164.all;
use ieee.numeric_std.all;

entity timingtest is
end timingtest;

architecture test of timingtest is

  -- internal signals
  signal reset, start, react : std_logic;
  signal leds : std_logic_vector(2 downto 0);
  signal cycles : std_logic_vector(7 downto 0);
  signal state_display : std_logic_vector(1 downto 0);

  -- Signals for hex display segments
	signal hex0_segments : UNSIGNED(6 downto 0);  
	signal hex1_segments : UNSIGNED(6 downto 0);

  -- Component declaration for timer
  component timer
    port (
      clk : in std_logic;
      reset : in std_logic;
      start : in std_logic;
      react : in std_logic;
      cycles : out std_logic_vector(7 downto 0);
      leds : out std_logic_vector(2 downto 0);
		curstate: out std_logic_vector(1 downto 0)
    );
  end component;

  component hexdisplay is
    port (
      a : in unsigned(3 downto 0);
      segments : out UNSIGNED(6 downto 0)
    );
	end component;

  -- signals for making the clock
  constant num_cycles : integer := 20;
  signal clk : std_logic := '1';
  
begin

  -- timed signals to create specific numbers
  reset <= '0', '1' after 7 ns;
  start <= '1', '0' after 10 ns, '1' after 20 ns, '0' after 75 ns, '1' after 85 ns;
  react <= '1', '0' after 25 ns, '1' after 35 ns, '0' after 170 ns, '1' after 180 ns;
  
  -- process and for-loop to generate a clock
  process begin
    for i in 1 to num_cycles loop
      clk <= not clk;
      wait for 5 ns;
      clk <= not clk;
      wait for 5 ns;
    end loop;
    wait;
  end process;

  -- Instantiate timer and hexdisplay components
  B0 : timer port map(clk, reset, start, react, cycles, leds, state_display);
  HEX0 : hexdisplay port map(a => unsigned(cycles(3 downto 0)), segments => hex0_segments);
  HEX1 : hexdisplay port map(a => unsigned(cycles(7 downto 4)), segments => hex1_segments);

end test;

project3/reaction/timingtest.vcd
$date
  Sun Oct 15 22:11:58 2023
$end
$version
  GHDL v0
$end
$timescale
  1 fs
$end
$scope module standard $end
$upscope $end
$scope module std_logic_1164 $end
$upscope $end
$scope module numeric_std $end
$upscope $end
$scope module timingtest $end
$var reg 1 ! reset $end
$var reg 1 " start $end
$var reg 1 # react $end
$var reg 3 $ leds[2:0] $end
$var reg 8 % cycles[7:0] $end
$var reg 2 & state_display[1:0] $end
$var reg 7 ' hex0_segments[6:0] $end
$var reg 7 ( hex1_segments[6:0] $end
$var reg 1 ) clk $end
$scope module b0 $end
$var reg 1 * clk $end
$var reg 1 + reset $end
$var reg 1 , start $end
$var reg 1 - react $end
$var reg 8 . cycles[7:0] $end
$var reg 3 / leds[2:0] $end
$var reg 2 0 curstate[1:0] $end
$var reg 8 1 count[7:0] $end
$comment internal_state is not handled $end
$upscope $end
$scope module hex0 $end
$var reg 4 2 a[3:0] $end
$var reg 7 3 segments[6:0] $end
$upscope $end
$scope module hex1 $end
$var reg 4 4 a[3:0] $end
$var reg 7 5 segments[6:0] $end
$upscope $end
$upscope $end
$enddefinitions $end
#0
0!
1"
1#
b100 $
b00000000 %
b00 &
b1000000 '
b1000000 (
0)
0*
0+
1,
1-
b00000000 .
b100 /
b00 0
b00000000 1
b0000 2
b1000000 3
b0000 4
b1000000 5
#5000000
1)
1*
#7000000
1!
1+
#10000000
0"
0)
0*
0,
#15000000
1)
1*
#20000000
1"
b010 $
b01 &
0)
0*
1,
b010 /
b01 0
#25000000
0#
1)
1*
0-
b11111111 1
#30000000
b100 $
b11111111 %
b00 &
b0001110 '
b0001110 (
0)
0*
b11111111 .
b100 /
b00 0
b1111 2
b0001110 3
b1111 4
b0001110 5
#35000000
1#
1)
1*
1-
#40000000
0)
0*
#45000000
1)
1*
#50000000
0)
0*
#55000000
1)
1*
#60000000
0)
0*
#65000000
1)
1*
#70000000
0)
0*
#75000000
0"
1)
1*
0,
#80000000
b010 $
b00000000 %
b01 &
b1000000 '
b1000000 (
0)
0*
b00000000 .
b010 /
b01 0
b0000 2
b1000000 3
b0000 4
b1000000 5
#85000000
1"
1)
1*
1,
b00000000 1
#90000000
0)
0*
#95000000
1)
1*
b00000001 1
#100000000
0)
0*
#105000000
1)
1*
b00000010 1
#110000000
0)
0*
#115000000
1)
1*
b00000011 1
#120000000
0)
0*
#125000000
1)
1*
b00000000 1
#130000000
b001 $
b10 &
0)
0*
b001 /
b10 0
b00000001 1
#135000000
b00000001 %
b1111001 '
1)
1*
b00000001 .
b00000010 1
b0001 2
b1111001 3
#140000000
b00000010 %
b0100100 '
0)
0*
b00000010 .
b00000011 1
b0010 2
b0100100 3
#145000000
b00000011 %
b0110000 '
1)
1*
b00000011 .
b00000100 1
b0011 2
b0110000 3
#150000000
b00000100 %
b0011001 '
0)
0*
b00000100 .
b00000101 1
b0100 2
b0011001 3
#155000000
b00000101 %
b0010010 '
1)
1*
b00000101 .
b00000110 1
b0101 2
b0010010 3
#160000000
b00000110 %
b0000010 '
0)
0*
b00000110 .
b00000111 1
b0110 2
b0000010 3
#165000000
b00000111 %
b1111000 '
1)
1*
b00000111 .
b00001000 1
b0111 2
b1111000 3
#170000000
0#
b00001000 %
b0000000 '
0)
0*
0-
b00001000 .
b1000 2
b0000000 3
#175000000
b100 $
b00 &
1)
1*
b100 /
b00 0
#180000000
1#
0)
0*
1-
